kash/__init__.py
kash/__main__.py
kash/actions/__init__.py
kash/actions/core/assistant_chat.py
kash/actions/core/chat.py
kash/actions/core/combine_docs.py
kash/actions/core/concat_docs.py
kash/actions/core/format_markdown_template.py
kash/actions/core/markdownify_html.py
kash/actions/core/minify_html.py
kash/actions/core/readability.py
kash/actions/core/render_as_html.py
kash/actions/core/save_sidematter_meta.py
kash/actions/core/show_webpage.py
kash/actions/core/strip_html.py
kash/actions/core/summarize_as_bullets.py
kash/actions/core/tabbed_webpage_config.py
kash/actions/core/tabbed_webpage_generate.py
kash/actions/core/zip_sidematter.py
kash/actions/meta/write_instructions.py
kash/actions/meta/write_new_action.py
kash/commands/__init__.py
kash/commands/base/basic_file_commands.py
kash/commands/base/browser_commands.py
kash/commands/base/debug_commands.py
kash/commands/base/diff_commands.py
kash/commands/base/files_command.py
kash/commands/base/general_commands.py
kash/commands/base/logs_commands.py
kash/commands/base/model_commands.py
kash/commands/base/reformat_command.py
kash/commands/base/search_command.py
kash/commands/base/show_command.py
kash/commands/extras/parse_uv_lock.py
kash/commands/extras/utils_commands.py
kash/commands/help/assistant_commands.py
kash/commands/help/doc_commands.py
kash/commands/help/help_commands.py
kash/commands/help/logo.py
kash/commands/help/welcome.py
kash/commands/workspace/selection_commands.py
kash/commands/workspace/workspace_commands.py
kash/config/__init__.py
kash/config/capture_output.py
kash/config/colors.py
kash/config/env_settings.py
kash/config/init.py
kash/config/lazy_imports.py
kash/config/logger.py
kash/config/logger_basic.py
kash/config/logo.txt
kash/config/server_config.py
kash/config/settings.py
kash/config/setup.py
kash/config/suppress_warnings.py
kash/config/text_styles.py
kash/config/unified_live.py
kash/config/warm_slow_imports.py
kash/docs/__init__.py
kash/docs/all_docs.py
kash/docs/load_actions_info.py
kash_shell-0.3.35.dist-info/METADATA
kash_shell-0.3.35.dist-info/WHEEL
kash_shell-0.3.35.dist-info/entry_points.txt
kash_shell-0.3.35.dist-info/licenses/LICENSE
kash_shell-0.3.35.dist-info/RECORD
