Metadata-Version: 2.4
Name: kash-shell
Version: 0.3.35
Summary: The knowledge agent shell (core)
Project-URL: Repository, https://github.com/jlevy/kash-shell
Author-email: Joshua Levy <joshua@cal.berkeley.edu>
License-Expression: AGPL-3.0-or-later
License-File: LICENSE
Classifier: Development Status :: 4 - Beta
Classifier: Intended Audience :: Developers
Classifier: Operating System :: OS Independent
Classifier: Programming Language :: Python
Classifier: Programming Language :: Python :: 3
Classifier: Programming Language :: Python :: 3.11
Classifier: Programming Language :: Python :: 3.12
Classifier: Programming Language :: Python :: 3.13
Classifier: Typing :: Typed
Requires-Python: <4.0,>=3.11
Requires-Dist: aiolimiter>=1.2.1
Requires-Dist: anyio>=4.8.0
Requires-Dist: audioop-lts>=0.2.1; python_version >= '3.13'
Requires-Dist: cachetools>=5.5.2
Requires-Dist: chopdiff>=0.2.6
Requires-Dist: clideps>=0.1.4
Requires-Dist: colour>=0.1.5
Requires-Dist: cssselect>=1.2.0
Requires-Dist: curl-cffi>=0.11.4
Requires-Dist: deepgram-sdk>=3.10.1
Requires-Dist: dunamai>=1.23.0
Requires-Dist: fastapi>=0.115.11
Requires-Dist: flowmark>=0.5.3
Requires-Dist: frontmatter-format>=0.2.3
Requires-Dist: funlog>=0.2.0
Requires-Dist: httpx[brotli]>=0.28.1
Requires-Dist: humanfriendly>=10.0
Requires-Dist: inquirerpy>=0.3.4
Requires-Dist: jinja2>=3.1.6
Requires-Dist: justext>=3.0.2
Requires-Dist: lazyasd>=0.1.4
Requires-Dist: litellm>=1.74.15.post1
Requires-Dist: markdownify>=0.13.1
Requires-Dist: mcp-proxy>=0.5.0
Requires-Dist: mcp>=1.6.0
Requires-Dist: openai==1.99.9
Requires-Dist: pandas>=2.2.3
Requires-Dist: patch-ng>=1.18.1
Requires-Dist: pathspec>=0.12.1
Requires-Dist: pluralizer>=1.2.0
Requires-Dist: prettyfmt>=0.4.1
Requires-Dist: prompt-toolkit>=3.0.50
Requires-Dist: pydantic>=2.10.6
Requires-Dist: pydub>=0.25.1
Requires-Dist: pygments>=2.19.1
Requires-Dist: pyperclip>=1.9.0
Requires-Dist: pyrate-limiter>=3.7.0
Requires-Dist: python-dotenv>=1.0.1
Requires-Dist: python-magic-bin>=0.4.14; platform_system == 'Windows'
Requires-Dist: python-magic>=0.4.27; platform_system == 'Linux' or platform_system == 'Darwin'
Requires-Dist: questionary>=2.0.0
Requires-Dist: readabilipy>=0.3.0
Requires-Dist: regex>=2024.11.6
Requires-Dist: rich-argparse>=1.7.0
Requires-Dist: rich>=14.0.0
Requires-Dist: ripgrepy>=2.1.0
Requires-Dist: selectolax>=0.3.32
Requires-Dist: send2trash>=1.8.3
Requires-Dist: setproctitle>=1.3.5
Requires-Dist: sidematter-format>=0.0.5
Requires-Dist: strif>=3.0.1
Requires-Dist: tenacity>=9.0.0
Requires-Dist: thefuzz>=0.22.1
Requires-Dist: tiktoken>=0.9.0
Requires-Dist: tldr>=3.3.0
Requires-Dist: tminify>=0.1.6
Requires-Dist: truststore>=0.10.4
Requires-Dist: typing-extensions>=4.12.2
Requires-Dist: uvicorn>=0.34.0
Requires-Dist: xonsh>=0.19.3
